<annotation>
	<folder>train2014</folder>
	<filename>COCO_train2014_000000000034.jpg</filename>
	<path>C:\Users\ASHIK\Downloads\dataset\train2014\COCO_train2014_000000000034.jpg</path>
	<source>
		<database>Unknown</database>
	</source>
	<size>
		<width>640</width>
		<height>425</height>
		<depth>3</depth>
	</size>
	<segmented>0</segmented>
	<object>
		<name>zebra</name>
		<pose>Unspecified</pose>
		<truncated>1</truncated>
		<difficult>0</difficult>
		<bndbox>
			<xmin>1</xmin>
			<ymin>11</ymin>
			<xmax>450</xmax>
			<ymax>398</ymax>
		</bndbox>
	</object>
</annotation>
